gaunn/__init__.py
gaunn/dataplotter.py
gaunn/demos.py
gaunn/ffnet.py
gaunn/loss_funcs.py
gaunn/nonlinearities.py
gaunn/optimizers.py
gaunn/rnnet.py
gaunn/version.py
gaunn/tests/__init__.py
gaunn/tests/test_demos.py
gaunn/tests/test_ffnet.py
gaunn/tests/test_gpu.py
gaunn/tests/test_optimizers.py
gaunn/tests/test_rnnet.py
gaunn-1.0.0.dist-info/DESCRIPTION.rst
gaunn-1.0.0.dist-info/METADATA
gaunn-1.0.0.dist-info/RECORD
gaunn-1.0.0.dist-info/WHEEL
gaunn-1.0.0.dist-info/metadata.json
gaunn-1.0.0.dist-info/top_level.txt
