Metadata-Version: 2.0
Name: gaunn
Version: 1.0.0
Summary: Feedforward and recurrent networks
Home-page: UNKNOWN
Author: Gautam.R
Author-email: gautamrbharadwaj@gmail.com
License: BSD
Keywords: neural network
Platform: UNKNOWN
